etc/systemd/system/lab-automation.service
etc/systemd/system/lab-automation.timer
lab_automation/__init__.py
lab_automation/confluence_utils.py
lab_automation/device_info_extractor.py
lab_automation/main.py
lab_automation/serial_utils.py
lab_automation/udev_parser.py
automation_viavi-1.6.dist-info/LICENSE
automation_viavi-1.6.dist-info/METADATA
automation_viavi-1.6.dist-info/WHEEL
automation_viavi-1.6.dist-info/entry_points.txt
automation_viavi-1.6.dist-info/top_level.txt
automation_viavi-1.6.dist-info/RECORD
