Metadata-Version: 2.1
Name: automation-viavi
Version: 1.6
Summary: Fetches state of the lab units and updates the Confluence page with them
Home-page: UNKNOWN
Author: Pomparau Renato
Author-email: renato.pomparau@viavisolutions.com
License: UNKNOWN
Platform: UNKNOWN
Classifier: Programming Language :: Python :: 3
Classifier: License :: OSI Approved :: MIT License
Classifier: Operating System :: OS Independent
Requires-Python: >=3.0
License-File: LICENSE
Requires-Dist: beautifulsoup4
Requires-Dist: pyserial
Requires-Dist: requests
